Metadata-Version: 1.1
Name: qrtt-data
Version: 0.0.1
Summary: Datasets for stocks and other financial instruments.
Home-page: https://data.qrtt.org
Author: Leopold W.
Author-email: lsw@lwco.com
License: UNKNOWN
Download-URL: https://github.com/leopoldsw/qrtt_data/archive/v0.01.tar.gz
Platform: UNKNOWN
